libname/__init__.py
libname/my_script.py
Arslan_lib-0.0.1.dist-info/METADATA
Arslan_lib-0.0.1.dist-info/WHEEL
Arslan_lib-0.0.1.dist-info/top_level.txt
Arslan_lib-0.0.1.dist-info/RECORD
